MANIFEST.in
README.md
setup.py
fh/__init__.py
fh/__init__.pyi
fhnmg.egg-info/PKG-INFO
fhnmg.egg-info/SOURCES.txt
fhnmg.egg-info/dependency_links.txt
fhnmg.egg-info/top_level.txt